bitnigma/__init__.py
bitnigma/__main__.py
bitnigma/generate.py
bitnigma/machine.py
bitnigma/reflectors.py
bitnigma/rotors.py
bitnigma-1.1.0.dist-info/DESCRIPTION.rst
bitnigma-1.1.0.dist-info/METADATA
bitnigma-1.1.0.dist-info/RECORD
bitnigma-1.1.0.dist-info/WHEEL
bitnigma-1.1.0.dist-info/metadata.json
bitnigma-1.1.0.dist-info/top_level.txt
