Metadata-Version: 2.0
Name: bitnigma
Version: 1.1.0
Summary: Python byte-enabled Enigma-like simulation.
Home-page: https://github.com/spgill/bitnigma
Author: Samuel P. Gillispie II
Author-email: spgill@vt.edu
License: MIT
Keywords: enigma machine encrypt encryption rotor rotors
Platform: UNKNOWN
Classifier: Environment :: Console
Classifier: Intended Audience :: Developers
Classifier: License :: OSI Approved :: MIT License
Classifier: Operating System :: OS Independent
Classifier: Programming Language :: Python :: 3
Classifier: Programming Language :: Python :: 3.6
